nmrPype/__init__.py
nmrPype/pype.py
nmrPype/fn/DECO.py
nmrPype/fn/DI.py
nmrPype/fn/DRAW.py
nmrPype/fn/FT.py
nmrPype/fn/HT.py
nmrPype/fn/PS.py
nmrPype/fn/SP.py
nmrPype/fn/TP.py
nmrPype/fn/ZF.py
nmrPype/fn/__init__.py
nmrPype/fn/function.py
nmrPype/nmrio/__init__.py
nmrPype/nmrio/fileiobase.py
nmrPype/nmrio/read.py
nmrPype/nmrio/write.py
nmrPype/nmrio/ccp4/__init__.py
nmrPype/nmrio/ccp4/ccp4.py
nmrPype/parse/__init__.py
nmrPype/parse/parser.py
nmrPype/utils/DataFrame.py
nmrPype/utils/__init__.py
nmrPype/utils/errorHandler.py
nmrPype/utils/fdata/__init__.py
nmrPype/utils/fdata/datamanip.py
nmrpype-1.0.9.dist-info/LICENSE
nmrpype-1.0.9.dist-info/METADATA
nmrpype-1.0.9.dist-info/WHEEL
nmrpype-1.0.9.dist-info/entry_points.txt
nmrpype-1.0.9.dist-info/top_level.txt
nmrpype-1.0.9.dist-info/RECORD
