Metadata-Version: 2.2
Name: nmrPype
Version: 1.0.9
Summary: Python implementation of Nuclear Magnetic Resonance (NMR) signal analysis program "nmrPipe"
Author: Micah Smith
Author-email: Micah Smith <mykahsmith21@gmail.com>, Frank Delaglio <frank.delaglio@nist.gov>
Maintainer-email: Micah Smith <mykahsmith21@gmail.com>
License: Copyright Notice and Statement for the nmrPype project
Project-URL: Homepage, https://github.com/PhiMykah/nmrPype
Project-URL: Documentation, https://phimykah.github.io/nmrpype/
Project-URL: Repository, https://github.com/PhiMykah/nmrPype.git
Project-URL: Issues, https://github.com/PhiMykah/nmrPype/issues
Keywords: nmr,decomposition
Classifier: Development Status :: 5 - Production/Stable
Classifier: License :: OSI Approved :: BSD License
Classifier: Operating System :: OS Independent
Classifier: Programming Language :: Python :: 3.10
Classifier: Programming Language :: Python :: 3.12
Requires-Python: >=3.10
License-File: LICENSE
Requires-Dist: numpy
Requires-Dist: scipy
Requires-Dist: matplotlib
Dynamic: author
